{
    "bookmarks.yazi": {
        "cargoLocks": null,
        "date": "2025-04-22",
        "extract": null,
        "name": "bookmarks.yazi",
        "passthru": null,
        "pinned": false,
        "src": {
            "deepClone": false,
            "fetchSubmodules": false,
            "leaveDotGit": false,
            "name": null,
            "owner": "DreamMaoMao",
            "repo": "bookmarks.yazi",
            "rev": "fa65ba2ec762c37096a5787bd9305b62827f2753",
            "sha256": "sha256-0bJw2bs1o3G2LpCwUV2HPYbNtyuI6IaoA42yl26YF8s=",
            "sparseCheckout": [],
            "type": "github"
        },
        "version": "fa65ba2ec762c37096a5787bd9305b62827f2753"
    },
    "fg.yazi": {
        "cargoLocks": null,
        "date": "2025-07-27",
        "extract": null,
        "name": "fg.yazi",
        "passthru": null,
        "pinned": false,
        "src": {
            "deepClone": false,
            "fetchSubmodules": false,
            "leaveDotGit": false,
            "name": null,
            "owner": "DreamMaoMao",
            "repo": "fg.yazi",
            "rev": "c201a3e1c0cda921c06019127886f16faef4b17e",
            "sha256": "sha256-PNZngyiWuzw2bmJ4v66er9HEAcD5z0Dr6iKYwcxJwf0=",
            "sparseCheckout": [],
            "type": "github"
        },
        "version": "c201a3e1c0cda921c06019127886f16faef4b17e"
    },
    "gvfs.yazi": {
        "cargoLocks": null,
        "date": "2025-08-29",
        "extract": null,
        "name": "gvfs.yazi",
        "passthru": null,
        "pinned": false,
        "src": {
            "deepClone": false,
            "fetchSubmodules": false,
            "leaveDotGit": false,
            "name": null,
            "owner": "boydaihungst",
            "repo": "gvfs.yazi",
            "rev": "b58c30588215093cb6f8b0dc4eed562894c091bc",
            "sha256": "sha256-koqbOTSEFL7O8J3PYcdv+XtPK8//m2nixuan6fWMR9Y=",
            "sparseCheckout": [],
            "type": "github"
        },
        "version": "b58c30588215093cb6f8b0dc4eed562894c091bc"
    },
    "nu_plugin_dbus": {
        "cargoLocks": null,
        "date": "2025-01-08",
        "extract": null,
        "name": "nu_plugin_dbus",
        "passthru": null,
        "pinned": false,
        "src": {
            "deepClone": false,
            "fetchSubmodules": false,
            "leaveDotGit": false,
            "name": null,
            "owner": "devyn",
            "repo": "nu_plugin_dbus",
            "rev": "ea17d3c5fbb74a06b143ef1b929f15bbf7e505a0",
            "sha256": "sha256-Ga+1zFwS/v+3iKVEz7TFmJjyBW/gq6leHeyH2vjawto=",
            "sparseCheckout": [],
            "type": "github"
        },
        "version": "ea17d3c5fbb74a06b143ef1b929f15bbf7e505a0"
    },
    "nu_plugin_dialog": {
        "cargoLocks": null,
        "date": "2024-02-03",
        "extract": null,
        "name": "nu_plugin_dialog",
        "passthru": null,
        "pinned": false,
        "src": {
            "deepClone": false,
            "fetchSubmodules": false,
            "leaveDotGit": false,
            "name": null,
            "owner": "Trivernis",
            "repo": "nu-plugin-dialog",
            "rev": "850310803eb7c9a4865ac6836f519f01c62b12b5",
            "sha256": "sha256-/KWEyVqXWgJfGIgFqXIBUqzA89FB/XDzn9aciknWApM=",
            "sparseCheckout": [],
            "type": "github"
        },
        "version": "850310803eb7c9a4865ac6836f519f01c62b12b5"
    },
    "nu_plugin_explore": {
        "cargoLocks": null,
        "date": "2025-03-24",
        "extract": null,
        "name": "nu_plugin_explore",
        "passthru": null,
        "pinned": false,
        "src": {
            "deepClone": false,
            "fetchSubmodules": false,
            "leaveDotGit": false,
            "name": null,
            "owner": "amtoine",
            "repo": "nu_plugin_explore",
            "rev": "fa5ab698463489bfc782077915f636661712a217",
            "sha256": "sha256-ziHjjNdLDgyrXOgFcQC34zjKX4dT7SvfS5xOrr+VeMc=",
            "sparseCheckout": [],
            "type": "github"
        },
        "version": "fa5ab698463489bfc782077915f636661712a217"
    },
    "nu_plugin_file": {
        "cargoLocks": null,
        "date": "2025-07-24",
        "extract": null,
        "name": "nu_plugin_file",
        "passthru": null,
        "pinned": false,
        "src": {
            "deepClone": false,
            "fetchSubmodules": false,
            "leaveDotGit": false,
            "name": null,
            "owner": "fdncred",
            "repo": "nu_plugin_file",
            "rev": "9331b9b163e5f14eb4142e1b088bb69601fff3cf",
            "sha256": "sha256-GyZlyEiOlL745fjMVPLEHwQGCFPq3LEhI9dezRp2PRc=",
            "sparseCheckout": [],
            "type": "github"
        },
        "version": "9331b9b163e5f14eb4142e1b088bb69601fff3cf"
    },
    "nu_plugin_port_list": {
        "cargoLocks": null,
        "date": "2025-02-10",
        "extract": null,
        "name": "nu_plugin_port_list",
        "passthru": null,
        "pinned": false,
        "src": {
            "deepClone": false,
            "fetchSubmodules": false,
            "leaveDotGit": false,
            "name": null,
            "owner": "FMotalleb",
            "repo": "nu_plugin_port_list",
            "rev": "f6fa5e59407d05317e7155dc9ca512ed17d12485",
            "sha256": "sha256-eGkUaS2MZQmowCkPB3Gow6f/MJ42b90lUpCEUeTxXfA=",
            "sparseCheckout": [],
            "type": "github"
        },
        "version": "f6fa5e59407d05317e7155dc9ca512ed17d12485"
    },
    "nu_plugin_prometheus": {
        "cargoLocks": null,
        "date": "2025-05-06",
        "extract": null,
        "name": "nu_plugin_prometheus",
        "passthru": null,
        "pinned": false,
        "src": {
            "deepClone": false,
            "fetchSubmodules": false,
            "leaveDotGit": false,
            "name": null,
            "owner": "drbrain",
            "repo": "nu_plugin_prometheus",
            "rev": "4a006851e56ceb474b93fc3f2d1980304065fce4",
            "sha256": "sha256-bcAzfSaSvxOvlyJAmaxLHaPbGxhvVShawZ8mGTEABAY=",
            "sparseCheckout": [],
            "type": "github"
        },
        "version": "4a006851e56ceb474b93fc3f2d1980304065fce4"
    },
    "nu_plugin_skim": {
        "cargoLocks": null,
        "date": "2025-09-02",
        "extract": null,
        "name": "nu_plugin_skim",
        "passthru": null,
        "pinned": false,
        "src": {
            "deepClone": false,
            "fetchSubmodules": false,
            "leaveDotGit": false,
            "name": null,
            "owner": "idanarye",
            "repo": "nu_plugin_skim",
            "rev": "6bbedb69891ee723e48b1693da58b92bdaeae265",
            "sha256": "sha256-zFY/HKBpMyGs8btrOa1loouEzgfzGYXYP2BADws3zmI=",
            "sparseCheckout": [],
            "type": "github"
        },
        "version": "6bbedb69891ee723e48b1693da58b92bdaeae265"
    },
    "officialPluginsSource": {
        "cargoLocks": null,
        "date": "2025-08-23",
        "extract": null,
        "name": "officialPluginsSource",
        "passthru": null,
        "pinned": false,
        "src": {
            "deepClone": false,
            "fetchSubmodules": false,
            "leaveDotGit": false,
            "name": null,
            "owner": "yazi-rs",
            "repo": "plugins",
            "rev": "d7588f6d29b5998733d5a71ec312c7248ba14555",
            "sha256": "sha256-9+58QhdM4HVOAfEC224TrPEx1N7F2VLGMxKVLAM4nJw=",
            "sparseCheckout": [],
            "type": "github"
        },
        "version": "d7588f6d29b5998733d5a71ec312c7248ba14555"
    },
    "open-with-cmd.yazi": {
        "cargoLocks": null,
        "date": "2025-02-09",
        "extract": null,
        "name": "open-with-cmd.yazi",
        "passthru": null,
        "pinned": false,
        "src": {
            "deepClone": false,
            "fetchSubmodules": false,
            "leaveDotGit": false,
            "name": null,
            "owner": "Ape",
            "repo": "open-with-cmd.yazi",
            "rev": "433cf301c36882c31032d3280ab0c94825fc5e9f",
            "sha256": "sha256-QazKfNEPFdkHwMrH4D+VMwj8fGXM8KHDdSvm1tik3dQ=",
            "sparseCheckout": [],
            "type": "github"
        },
        "version": "433cf301c36882c31032d3280ab0c94825fc5e9f"
    },
    "searchjump.yazi": {
        "cargoLocks": null,
        "date": "2025-07-11",
        "extract": null,
        "name": "searchjump.yazi",
        "passthru": null,
        "pinned": false,
        "src": {
            "deepClone": false,
            "fetchSubmodules": false,
            "leaveDotGit": false,
            "name": null,
            "owner": "DreamMaoMao",
            "repo": "searchjump.yazi",
            "rev": "7fafec3e667f2b93d3ad21989ef75bbf95bb43fc",
            "sha256": "sha256-zH/X7YUpfDiOcEKuXG4J1MZFj3Dv28rWOi9XEod8NNo=",
            "sparseCheckout": [],
            "type": "github"
        },
        "version": "7fafec3e667f2b93d3ad21989ef75bbf95bb43fc"
    },
    "what-size.yazi": {
        "cargoLocks": null,
        "date": "2025-06-19",
        "extract": null,
        "name": "what-size.yazi",
        "passthru": null,
        "pinned": false,
        "src": {
            "deepClone": false,
            "fetchSubmodules": false,
            "leaveDotGit": false,
            "name": null,
            "owner": "pirafrank",
            "repo": "what-size.yazi",
            "rev": "d8966568f2a80394bf1f9a1ace6708ddd4cc8154",
            "sha256": "sha256-s2BifzWr/uewDI6Bowy7J+5LrID6I6OFEA5BrlOPNcM=",
            "sparseCheckout": [],
            "type": "github"
        },
        "version": "d8966568f2a80394bf1f9a1ace6708ddd4cc8154"
    },
    "whoosh.yazi": {
        "cargoLocks": null,
        "date": "2025-09-01",
        "extract": null,
        "name": "whoosh.yazi",
        "passthru": null,
        "pinned": false,
        "src": {
            "deepClone": false,
            "fetchSubmodules": false,
            "leaveDotGit": false,
            "name": null,
            "owner": "WhoSowSee",
            "repo": "whoosh.yazi",
            "rev": "527ab13e524ff73c164032fce768c1ef2851d28d",
            "sha256": "sha256-4COD1H5BZU7HXSMbQ5XpzUpLhzSq4bf1XYR01WcvUwE=",
            "sparseCheckout": [],
            "type": "github"
        },
        "version": "527ab13e524ff73c164032fce768c1ef2851d28d"
    },
    "wl-clipboard.yazi": {
        "cargoLocks": null,
        "date": "2025-08-30",
        "extract": null,
        "name": "wl-clipboard.yazi",
        "passthru": null,
        "pinned": false,
        "src": {
            "deepClone": false,
            "fetchSubmodules": false,
            "leaveDotGit": false,
            "name": null,
            "owner": "grappas",
            "repo": "wl-clipboard.yazi",
            "rev": "e9a38e47d07549968019702bdafdc4ed07151b7d",
            "sha256": "sha256-3PRQl4TvuOe5DwVi1gmtmfTOEVZWRayijIbnPgaR3L8=",
            "sparseCheckout": [],
            "type": "github"
        },
        "version": "e9a38e47d07549968019702bdafdc4ed07151b7d"
    }
}